djangowind/__init__.py
djangowind/auth.py
djangowind/context.py
djangowind/models.py
djangowind/urls.py
djangowind/views.py
djangowind-1.2.5.dist-info/LICENSE
djangowind-1.2.5.dist-info/METADATA
djangowind-1.2.5.dist-info/WHEEL
djangowind-1.2.5.dist-info/top_level.txt
djangowind-1.2.5.dist-info/RECORD
