Metadata-Version: 2.1
Name: djangowind
Version: 1.2.5
Summary: Django Authentication backend for CAS
Home-page: https://github.com/ccnmtl/djangowind
Author: Anders Pearson
Author-email: ctl-dev@columbia.edu
License: BSD
Platform: any
License-File: LICENSE
